[
  {
    "id": 1,
    "name": "Charmander",
    "type_primary": "fire",
    "type_secondary": "flying",
    "weakness_due_to_weather": false,
    "weather_summary": null
  },
  {
    "id": 2,
    "name": "Pikachu",
    "type_primary": "electric",
    "type_secondary": null,
    "weakness_due_to_weather": false,
    "weather_summary": null
  },
  {
    "id": 3,
    "name": "Squirtle",
    "type_primary": "water",
    "type_secondary": null,
    "weakness_due_to_weather": false,
    "weather_summary": null
  },
  {
    "id": 4,
    "name": "Eevee",
    "type_primary": "normal",
    "type_secondary": null,
    "weakness_due_to_weather": false,
    "weather_summary": null
  },
  {
    "id": 5,
    "name": "Vaporeon",
    "type_primary": "water",
    "type_secondary": "normal",
    "weakness_due_to_weather": false,
    "weather_summary": null
  }
]